pthugefileviewer/__init__.py
pthugefileviewer/hugefilevieweruicontrol.py
pthugefileviewer/py.typed
pthugefileviewer-0.5.0.data/data/share/doc/python-pthugefileviewer/AUTHORS
pthugefileviewer-0.5.0.data/data/share/doc/python-pthugefileviewer/LICENSE
pthugefileviewer-0.5.0.data/data/share/doc/python-pthugefileviewer/README.md
pthugefileviewer-0.5.0.data/scripts/hfv-regexbuild
pthugefileviewer-0.5.0.data/scripts/hfv-view
pthugefileviewer-0.5.0.dist-info/LICENSE
pthugefileviewer-0.5.0.dist-info/METADATA
pthugefileviewer-0.5.0.dist-info/WHEEL
pthugefileviewer-0.5.0.dist-info/top_level.txt
pthugefileviewer-0.5.0.dist-info/RECORD
