Metadata-Version: 2.1
Name: pthugefileviewer
Version: 0.5.0
Summary: Huge file viewer control for prompt-toolkit
Home-page: http://github.com/lpenz/pthugefileviewer
Author: "Leandro Lisboa Penz"
Author-email: "lpenz@lpenz.org"
License: MIT
Classifier: Development Status :: 1 - Planning
Classifier: Environment :: Console
Classifier: License :: OSI Approved :: MIT License
Classifier: Operating System :: POSIX :: Linux
Classifier: Programming Language :: Python :: 3
Requires-Python: >=3.9
License-File: LICENSE
Requires-Dist: prompt-toolkit >=3
Provides-Extra: test
Requires-Dist: pytest ; extra == 'test'
Requires-Dist: pytest-cov ; extra == 'test'
